suzhou.py
suzhounumerals-1.0.dist-info/licenses/LICENSE
suzhounumerals-1.0.dist-info/METADATA
suzhounumerals-1.0.dist-info/WHEEL
suzhounumerals-1.0.dist-info/top_level.txt
suzhounumerals-1.0.dist-info/RECORD
