Metadata-Version: 2.4
Name: suzhounumerals
Version: 1.0
Author: Hayden Wong
License-Expression: GPL-3.0-or-later
Project-URL: Homepage, https://github.com/haydenwong7bm/suzhounumerals
Project-URL: Documentation, https://github.com/haydenwong7bm/suzhounumerals
Project-URL: Source, https://github.com/haydenwong7bm/suzhounumerals
Project-URL: Tracker, https://github.com/haydenwong7bm/suzhounumerals/issues
Keywords: suzhounumerals
Classifier: Programming Language :: Python :: 3
Classifier: Operating System :: OS Independent
Requires-Python: >=3.7
License-File: LICENSE
Dynamic: license-file
